pyelasticache_client-0.1.3.dist-info/DESCRIPTION.rst
pyelasticache_client-0.1.3.dist-info/METADATA
pyelasticache_client-0.1.3.dist-info/RECORD
pyelasticache_client-0.1.3.dist-info/WHEEL
pyelasticache_client-0.1.3.dist-info/metadata.json
pyelasticache_client-0.1.3.dist-info/top_level.txt
pymemcache/__init__.py
pymemcache/exceptions.py
pymemcache/fallback.py
pymemcache/pool.py
pymemcache/serde.py
pymemcache/client/__init__.py
pymemcache/client/autodiscovery.py
pymemcache/client/base.py
pymemcache/client/consistenthasher.py
pymemcache/client/hash.py
pymemcache/client/ketama.py
pymemcache/client/murmur3.py
pymemcache/client/rendezvous.py
pymemcache/test/__init__.py
pymemcache/test/conftest.py
pymemcache/test/test_benchmark.py
pymemcache/test/test_client.py
pymemcache/test/test_client_consistent.py
pymemcache/test/test_client_hash.py
pymemcache/test/test_cluster.py
pymemcache/test/test_integration.py
pymemcache/test/test_rendezvous.py
pymemcache/test/test_utils.py
pymemcache/test/utils.py
