Metadata-Version: 2.0
Name: pyelasticache-client
Version: 0.1.3
Summary: A comprehensive, fast, pure Python memcached client
Home-page: https://github.com/touchvie/pyelasticache_client
Author: David Fierro, Guillermo Menendez, N. Angulo & Charles Gordon
Author-email: info@touchvie.com
License: Apache License 2.0
Keywords: AWS,elasticache,memcached,autodiscovery
Platform: UNKNOWN
Classifier: Programming Language :: Python
Classifier: Programming Language :: Python :: 2.6
Classifier: Programming Language :: Python :: 2.7
Classifier: Programming Language :: Python :: 3.3
Classifier: Programming Language :: Python :: 3.4
Classifier: Programming Language :: Python :: 3.5
Classifier: Programming Language :: Python :: Implementation :: PyPy
Classifier: License :: OSI Approved :: Apache Software License
Classifier: Topic :: Database
Requires-Dist: six
Requires-Dist: sortedcontainers
